fastflyer/__info__.py
fastflyer/__init__.py
fastflyer/authorize.py
fastflyer/cache.py
fastflyer/configure.py
fastflyer/database.py
fastflyer/discovery.py
fastflyer/exceptions.py
fastflyer/main.py
fastflyer/mcp.py
fastflyer/middleware.py
fastflyer/router.py
fastflyer/scheduler.py
fastflyer/schemas.py
fastflyer/settings.py
fastflyer/trace.py
fastflyer/utils.py
fastflyer/base/__init__.py
fastflyer/base/docs.py
fastflyer/base/tasks.py
fastflyer/static/License-icon.svg
fastflyer/static/Python-3.6.8+-icon.svg
fastflyer/static/bench.png
fastflyer/static/favicon.ico
fastflyer/static/logo.png
fastflyer/static/redoc.png
fastflyer/static/redoc.standalone.js
fastflyer/static/show_demo.png
fastflyer/static/swagger-ui-bundle.js
fastflyer/static/swagger-ui.css
fastflyer/static/swagger.png
fastflyer/tools/entrypoint.py
fastflyer/tools/template/__init__.py
fastflyer/tools/template/openapi/.dockerignore
fastflyer/tools/template/openapi/.gitignore
fastflyer/tools/template/openapi/Dockerfile
fastflyer/tools/template/openapi/README.md
fastflyer/tools/template/openapi/__init__.py
fastflyer/tools/template/openapi/dependences.txt
fastflyer/tools/template/openapi/dev_ctrl.sh
fastflyer/tools/template/openapi/logo.png
fastflyer/tools/template/openapi/main.py
fastflyer/tools/template/openapi/requirements.txt
fastflyer/tools/template/openapi/settings.py
fastflyer/tools/template/openapi/start-reload.sh
fastflyer/tools/template/openapi/start.sh
fastflyer/tools/template/openapi/app/__init__.py
fastflyer/tools/template/openapi/app/items/README.md
fastflyer/tools/template/openapi/app/items/__init__.py
fastflyer/tools/template/openapi/app/items/module.py
fastflyer/tools/template/openapi/app/items/router.py
fastflyer/tools/template/openapi/app/items/schema.py
fastflyer/tools/template/openapi/app/tasks/README.md
fastflyer/tools/template/openapi/app/tasks/__init__.py
fastflyer/tools/template/openapi/app/tasks/module.py
fastflyer/tools/template/openapi/app/users/README.md
fastflyer-0.1.37.dist-info/licenses/LICENSE
fastflyer-0.1.37.dist-info/METADATA
fastflyer-0.1.37.dist-info/WHEEL
fastflyer-0.1.37.dist-info/entry_points.txt
fastflyer-0.1.37.dist-info/top_level.txt
fastflyer-0.1.37.dist-info/zip-safe
fastflyer-0.1.37.dist-info/RECORD
