Metadata-Version: 2.4
Name: fastflyer
Version: 0.1.37
Summary: FastFlyer — 轻量级API开发框架
Home-page: https://github.com/jagerzhang/fastflyer.git
Author: Jagerzhang
Author-email: im@zhang.ge
License: Apache 2.0
Classifier: Programming Language :: Python :: 3
Requires-Python: >=3, <4
License-File: LICENSE
Requires-Dist: fastapi>=0.69.0
Requires-Dist: uvicorn>=0.14.0
Requires-Dist: gunicorn>=21.2.0
Requires-Dist: httptools>=0.1.2
Requires-Dist: fastkit>=0.1.15
Requires-Dist: opentelemetry-exporter-otlp
Requires-Dist: opentelemetry-instrumentation-fastapi
Requires-Dist: opentelemetry-instrumentation-logging
Requires-Dist: opentelemetry-instrumentation-requests
Requires-Dist: opentelemetry-instrumentation-httpx
Requires-Dist: opentelemetry-instrumentation-redis
Requires-Dist: opentelemetry-instrumentation-kafka-python
Requires-Dist: opentelemetry-instrumentation-pymysql
Requires-Dist: opentelemetry-instrumentation-sqlalchemy
Requires-Dist: opentelemetry-instrumentation-threading
Requires-Dist: fastapi-mcp
Dynamic: author
Dynamic: author-email
Dynamic: classifier
Dynamic: description
Dynamic: description-content-type
Dynamic: home-page
Dynamic: license
Dynamic: license-file
Dynamic: requires-dist
Dynamic: requires-python
Dynamic: summary
